image_classifier_3d/__init__.py
image_classifier_3d/proj_tester.py
image_classifier_3d/proj_trainer.py
image_classifier_3d/bin/__init__.py
image_classifier_3d/bin/run_classifier.py
image_classifier_3d/data_loader/__init__.py
image_classifier_3d/data_loader/universal_loader.py
image_classifier_3d/data_loader/utils.py
image_classifier_3d/models/__init__.py
image_classifier_3d/models/build_classifier.py
image_classifier_3d/models/densenet.py
image_classifier_3d/models/model_mnist.py
image_classifier_3d/models/resnet.py
image_classifier_3d/models/resnet_GN.py
image_classifier_3d/utils/__init__.py
image_classifier_3d/utils/io_utils.py
image_classifier_3d/utils/misc_utils.py
image_classifier_3d-0.1.2.dist-info/LICENSE
image_classifier_3d-0.1.2.dist-info/METADATA
image_classifier_3d-0.1.2.dist-info/WHEEL
image_classifier_3d-0.1.2.dist-info/entry_points.txt
image_classifier_3d-0.1.2.dist-info/top_level.txt
image_classifier_3d-0.1.2.dist-info/RECORD
